queue_manager
worker_helpers
workers
