Metadata-Version: 1.0
Name: queue-mfc-manager
Version: 0.4.2
Summary: Simple queue manager for me and you!
Home-page: https://github.com/seregagavrilov/queue_mfc_manager
Author: Sergey Gavrilov
Author-email: sergeigavrilov123@gmail.com
License: MIT
Platform: UNKNOWN
